{
  "infobox": {
    "Title": [
      "Galio"
    ],
    "Nickname": [
      "Galio Justice Justice"
    ],
    "Alias(es)": [
      "The Colossus",
      "The Titan Who 'Ate Magic'"
    ],
    "Species": [
      "Petricite Golem"
    ],
    "Pronoun": [
      "He/Him"
    ],
    "Age": [
      "Current648 – 705 years old Timeline Born292 AN – 349 AN Edit"
    ],
    "Weapon": [
      "Petricite Body",
      "Anti-Magic Bulwark",
      "Shield of Durand"
    ],
    "Status": [
      "Alive (Constructed)"
    ],
    "Place of origin": [
      "Great City",
      "Demacia"
    ],
    "Current residence": [
      "Memorial Road",
      "Great City of Demacia"
    ],
    "Family": [
      "Arcturus J. Durand † (Creator)"
    ],
    "Occupation": [
      "Anti-Magic Guardian",
      "Demacia's Protector"
    ],
    "Region": [
      "Demacia"
    ],
    "Faction": [
      "House Durand"
    ],
    "Korean name": [
      "갈리오"
    ],
    "Chinese name": [
      "加里奥"
    ],
    "Japanese name": [
      "ガリオ"
    ],
    "Russian name": [
      "Галио"
    ],
    "Greek name": [
      "Γκάλιο"
    ],
    "Related character": [
      "Poppy",
      "Kayle",
      "Morgana",
      "Sion",
      "Shyvana",
      "Lux",
      "Ryze",
      "Garen",
      "Sylas"
    ]
  },
  "mainContent": [
    {
      "number": "1",
      "title": "Background",
      "link": "#Background",
      "children": [
        {
          "number": "1.1",
          "title": "Early Life",
          "link": "#Early_Life",
          "children": [],
          "textContent": "Commissioned by the Demacian military some time after the Founding, the master craftsman Arcturus J. Durand sculpted an enormous winged statue to serve as a protective petricite shield against enemy mages. After two years of hard work, Durand unveiled Galio as his masterpiece, which would both serve a national symbol for Demacia and prove vital to the nation's defense. In battle, the statue would be transported to the front lines to neutralize enemy mages. At the Battle of the Greenfang Mountains, the magical onslaught of warmages known as the Arcane Fist infused Galio with enough energy to awaken for the first time. He fought alongside Demacian soldiers, destroying the enemy force before the magic faded and he returned to inert stone. While unable to move, his mind remained awake, longing to relive that moment."
        },
        {
          "number": "1.2",
          "title": "Stagnation",
          "link": "#Stagnation",
          "children": [],
          "textContent": "For decades, Galio would remain dormant, aware but unable to move without a strong magical presence. He was often transported to battlefields, only to return without awakening. One day, during a clash with Freljordian barbarians, he spotted a titanic chained beast and felt his old excitement. A sorcerer’s devastating magic finally stirred him to life. Galio charged into the fray, smashing siege engines and challenging the monstrous creature. Though he relished the fight, the cries of his Demacian soldiers drew him away. He crushed the enemy mage, routing the invaders, but the loss of magical energy sent him back into dormancy, questioning why he possessed no magic of his own."
        },
        {
          "number": "1.3",
          "title": "Meeting Lux",
          "link": "#Meeting_Lux",
          "children": [],
          "textContent": "Years later, Luxanna Crownguard, a thirteen-year-old noble girl hiding her dangerous light magic, fled her home in fear of discovery. She wandered into the palace gardens and approached the Galio monument, accidentally awakening him with her magic. The two formed a warm, if brief, companionship: Galio marveled at her light, and Lux delighted in his protection. Their time together was cut short when Lux slipped away from the colossus to evade the annullers, yet Galio soon found her again, rescuing her from a band of armed men in the woods. They shared a peaceful moment watching the sunrise before she returned home, where her mother had summoned an annuller. Lux refused to be “cured,” choosing to live with her magic in secret."
        },
        {
          "number": "1.4",
          "title": "Defending against the Winter's Claw",
          "link": "#Defending_against_the_Winter's_Claw",
          "children": [],
          "textContent": ""
        }
      ]
    },
    {
      "number": "2",
      "title": "Appearance",
      "link": "#Appearance",
      "children": [],
      "textContent": "Galio takes the appearance of a large muscular gargoyle, with wing motifs reminiscent to the winged sister during Demacia's early years. His body is mostly made of petricite, which is of a white marble-like color, Some gold elements are present around his body, giving him a regal appearance."
    },
    {
      "number": "3",
      "title": "Personality",
      "link": "#Personality",
      "children": [],
      "textContent": "Galio, when active, has a cheerful personality, always eager to help people in need, as well as fight whenever called upon. He has no particular fondness for most mages, as most of his encounters with them are from opposing armies."
    },
    {
      "number": "4",
      "title": "Abilities",
      "link": "#Abilities",
      "children": [],
      "textContent": ""
    },
    {
      "number": "5",
      "title": "Relations",
      "link": "#Relations",
      "children": [
        {
          "number": "5.1",
          "title": "Arcturus J. Durand",
          "link": "#Arcturus_J._Durand",
          "children": [],
          "textContent": ""
        },
        {
          "number": "5.2",
          "title": "Vladimir",
          "link": "#Vladimir",
          "children": [],
          "textContent": "Vladimir has a portrait in his gallery which depicts him gravely wounded in battle against an enormous statue of ivory stone, which was possibly Galio."
        },
        {
          "number": "5.3",
          "title": "Luxanna Crownguard",
          "link": "#Luxanna_Crownguard",
          "children": [],
          "textContent": "Like most Demacians, the Crownguards made an annual pilgrimage to visit Galio on the Memorial Road. This is how he first became aware of Lux, reacting to the growing presence of the light magic within her each year ever since she was a toddler. Galio sees Lux as the only mage he likes and has become a sort of guardian to her. Lux is apparently the first person to have an actual conversation with him. She was 13 years old at the time."
        }
      ]
    },
    {
      "number": "6",
      "title": "Read More",
      "link": "#Read_More",
      "children": [
        {
          "number": "6.1",
          "title": "Biography",
          "link": "#Biography",
          "children": [],
          "textContent": ""
        },
        {
          "number": "6.2",
          "title": "Starring Champion",
          "link": "#Starring_Champion",
          "children": [],
          "textContent": ""
        },
        {
          "number": "6.3",
          "title": "Mentioned Champion",
          "link": "#Mentioned_Champion",
          "children": [],
          "textContent": ""
        },
        {
          "number": "6.4",
          "title": "Alternate Universes",
          "link": "#Alternate_Universes",
          "children": [],
          "textContent": ""
        }
      ]
    },
    {
      "number": "7",
      "title": "Trivia",
      "link": "#Trivia",
      "children": [],
      "textContent": ""
    },
    {
      "number": "8",
      "title": "Change log",
      "link": "#Change_log",
      "children": [],
      "textContent": "The following change log is for the Character blurb found at the top of the article:\n\nFor historical versions of other stories, please see each story's respective change log."
    },
    {
      "number": "9",
      "title": "References",
      "link": "#References",
      "children": [],
      "textContent": ""
    },
    {
      "number": "10",
      "title": "See also",
      "link": "#See_also",
      "children": [],
      "textContent": ""
    }
  ],
  "gliner_entities": {
    "Champion": [
      "Galio",
      "Vladimir"
    ],
    "Region": [
      "Greenfang Mountains"
    ],
    "Weapon": [
      "Arcane Fist",
      "annuller",
      "annullers",
      "siege engines"
    ],
    "Title": [
      "guardian",
      "Character blurb"
    ],
    "Organization": [
      "Demacian soldiers",
      "enemy mages",
      "Crownguards",
      "opposing armies",
      "Demacian military"
    ],
    "Family": []
  }
}