{
  "infobox": {
    "Title": [
      "Samira"
    ],
    "Nickname": [
      "Sam",
      "8 Girl"
    ],
    "Alias(es)": [
      "The Desert Rose"
    ],
    "Species": [
      "Human"
    ],
    "Pronoun": [
      "She/Her"
    ],
    "Age": [
      "Current33 years old Timeline Born964 AN Edit [1]"
    ],
    "Weapon": [
      "Blaze & Thorn",
      "Vanquish"
    ],
    "Status": [
      "Alive"
    ],
    "Place of origin": [
      "Amakra",
      "Shurima"
    ],
    "Current residence": [
      "Noxus"
    ],
    "Family": [
      "Unnamed Mother",
      "Unnamed Father"
    ],
    "Occupation": [
      "Mercenary",
      "Adventurer",
      "Street Performer"
    ],
    "Region": [
      "Shurima",
      "Noxus"
    ],
    "Korean name": [
      "사미라"
    ],
    "Chinese name": [
      "莎弥拉"
    ],
    "Japanese name": [
      "サミーラ"
    ],
    "Russian name": [
      "Самира"
    ],
    "Greek name": [
      "Σαμίρα"
    ],
    "Related character": [
      "Darius",
      "LeBlanc",
      "Rell",
      "Sett",
      "Xerath",
      "Viego",
      "Jack",
      "Elise"
    ]
  },
  "mainContent": [
    {
      "number": "1",
      "title": "Background",
      "link": "#Background",
      "children": [
        {
          "number": "1.1",
          "title": "Early Life",
          "link": "#Early_Life",
          "children": [
            {
              "number": "1.1.1",
              "title": "Taking Refuge in Bel'zhun",
              "link": "#Taking_Refuge_in_Bel'zhun",
              "children": [],
              "textContent": ""
            },
            {
              "number": "1.1.2",
              "title": "Attack at Rokrund",
              "link": "#Attack_at_Rokrund",
              "children": [],
              "textContent": "Under direct orders from the capital, Indari's unit was sent to crush a secessionist uprising at the Rokrund Plains. When the warband located the enemy stronghold and found the rebel leader, the fortress exploded with Indari inside. Samira, in an attempt to save her captain, dove headfirst into the stronghold as it collapsed, feeling no sense of fear and wasting no time in recovering her captain. Miraculously, the two of them actually survived the explosion, though Samira suffered a permanent injury to her right eye while Indari lost the ability to use her legs. Frustrated with their failure, Indari gathered as many survivors as she could but officially disbanded the unit."
            },
            {
              "number": "1.1.3",
              "title": "Becoming a Mercenary",
              "link": "#Becoming_a_Mercenary",
              "children": [],
              "textContent": "Samira, now discharged and sent back to Bel'zhun, continued to desire the life of action she once had while in Indari's warband, no longer pleased with a quiet stable life within the port city. Seeking her former captain out, Samira returned to the Noxian capital and met up with Indari, proposing that they form a new partnership. With Indari's connections to the military and the Noxian noble houses, she could operate behind the scenes while Samira acts as a high-stakes mercenary under Indari's command. Reluctantly, she agreed, but refused to grant Samira any field support in fear of making the same mistakes as she did in Rokrund."
            }
          ]
        },
        {
          "number": "1.2",
          "title": "Modern History",
          "link": "#Modern_History",
          "children": [
            {
              "number": "1.2.1",
              "title": "The Hunt for Rell",
              "link": "#The_Hunt_for_Rell",
              "children": [],
              "textContent": "Samira was eventually assigned a mission to locate a dangerous weapon that threatened the Noxian empire, which was located within a compound deep in the southern jungles of Qualthala, and leave no survivors. Before her mission, Samira visited a weapons shop called Lani and Miel Munitions, accompanied by Indari. There, she met two Zaunite weaponsmiths named Lani and Miel, who also had apprentices that moonlit as tattoo artists. In the shop, Samira saw a pair of notably flashy pistols displayed in a glass case and instantly decided to buy them without much thought, which annoyed Indari.\n\nAfter buying a new set of equipment for the job, Samira set off to the compound in Qualthala, finding a building devoid of markings with wooden doors that were already smashed to pieces as well as strangely warped pieces of metal scattered around. She encountered and killed two guards in the compound before alerting some warmasons and executing them in a flurry of gunfire. After hopping over a crushed balcony and landing in an open courtyard, Samira noticed another building in the distance that also had its doors smashed apart, noting that someone else must've beat her to the weapon she was assigned to locate.\n\nTwo soldiers wielding axes and riding massive basilisks charged towards Samira in the courtyard, making note of a null kid and questioning if Rell sent Samira to the compound to 'clean up the mess,' a name that Samira had never heard of but also didn't care much for as she managed to kill one of the riders and mount his basilisk, jousting with the second rider before using her specialized blade to pierce through his armor by empowering it with black powder.\n\nFinally entering the building, Samira found a crumbling stairway and followed it into a stone prison cell full of even more warped pieces of metal, with the door completely obliterated while the back wall had a massive hole opened into the jungle. Examining the room more, she noticed a small cot seemingly fit for a child, which was split by jagged shards of metal. Here, she took a seat and drank from her flask, realizing the weapon had gotten away but congratulating it for 'getting her attention,' seemingly vowing to continue her search.\n\nWeeks later, Samira returned to the weapons shop with Indari to get a new tattoo drawn by one of the apprentices in the store. Indari questioned Samira on how her new equipment performed on the mission, to which Samira answered that her new guns were exquisite and revealed she intended to be using them for a long time. After paying for the tattoo and leaving, the tattoo artist revealed himself to actually be LeBlanc in disguise, who had been working with Captain Indari and commanded her to give Samira whatever resources she needs, noting her importance to the empire and the missions she would be sent off on."
            }
          ]
        },
        {
          "number": "1.3",
          "title": "Recent Events",
          "link": "#Recent_Events",
          "children": [
            {
              "number": "1.3.1",
              "title": "The Ruination",
              "link": "#The_Ruination",
              "children": [],
              "textContent": "Samira was present when the Ruined King managed to get a hold of Senna, causing the Black Mist to spread violently across Runeterra. During this, she was near the Hand of Noxus Darius as he commanded his army the Trifarian Legion. When the Black Mist manifested in Noxus, it appeared atop the Immortal Bastion and nearly got a a hold of her before Darius pushed her out of the way. As the Black Mist quickly spread across the city, hoards of Wraiths appeared and attacked the Trifarian Legion, causing Samira to join in the fight to assist her fellow Noxians. During this however, the Black Mist took a hold of Darius's mind, controlling him under Viego's will and forcing him to attack Samira, which she narrowly evaded. During the fight, the Black Mist suddenly ceased, allowing Samira and a weakened Darius to recover while looking cautiously at the Immortal Bastion, where the Black Mist poured into Noxus from."
            },
            {
              "number": "1.3.2",
              "title": "Mission in Navori",
              "link": "#Mission_in_Navori",
              "children": [],
              "textContent": "At some point, Samira is sent on a mission to the Ionian city of Qayanvi, located in the province of Navori. Samira was sent to locate a 8 debt evader wanted by the empire, said to be hiding out in Navori and attending a massive fighting pit event being hosted by the Ionian crime boss Sett. This mission however required some backup, as Indari gathered a band of other mercenaries to assist her, including Lani, Miel, 4 Dashing Dandy, 3 Dame the Despoiler, 4 Inferna, 2 Father Fury, a 3 brazen buccaneer, a 1 bladed ballerina and even Indari herself. The event is extremely exclusive, being invite-only and with tight security. However, Indari manages to pull a few strings thanks to her many connections, granting Samira and her team an invite to the fighting pits.\n\nWhen an infamous Bilgewater boxer named Jack crashes the event and personally challenges Sett, chaos ensues in the fighting pits as Samira's team fights off Jack's crew. During this, their target reveals himself, allowing Samira to pursue him through the chaos and capture her target."
            }
          ]
        }
      ]
    },
    {
      "number": "2",
      "title": "Appearance",
      "link": "#Appearance",
      "children": [],
      "textContent": "Samira is a beautiful woman with tanned skin, she has an athletic and voluptuous physique, a round face with a mole on the right side of her lip, thick lips, wears an eyepatch over her right eye and her left eye is emerald green. Long black hair which she wears braided in a French braid that falls over her right shoulder on which she has woven golden jewels.\n\nShe has a slightly revealing uniform of red and black colors with leather boots, a short skirt and a short t-shirt that reveals her abdomen as well as several tattoos on her left arm."
    },
    {
      "number": "3",
      "title": "Personality",
      "link": "#Personality",
      "children": [],
      "textContent": "Samira is quite a stubborn and impulsive woman, determined to show that she is not afraid of danger, enjoying the adrenaline rush that it caused her, despite everything she cared a lot about her parents wishing they were safe."
    },
    {
      "number": "4",
      "title": "Abilities",
      "link": "#Abilities",
      "children": [],
      "textContent": ""
    },
    {
      "number": "5",
      "title": "Relations",
      "link": "#Relations",
      "children": [
        {
          "number": "5.1",
          "title": "Parents",
          "link": "#Parents",
          "children": [],
          "textContent": "Samira performed in street performances alongside her parents when she was young. While she enjoyed performing, they wished her to live a more stable life. When her family immigrated to Noxus, she had to support her injured parents by herself but struggled to make ends meet. After becoming a mercenary, Samira told her parents about her tattoos and impressive feats. Samira is close to her mother, recalling the stories and advice she gave her when she was young."
        },
        {
          "number": "5.2",
          "title": "Xerath",
          "link": "#Xerath",
          "children": [],
          "textContent": "Samira was forced to evacuate Amakra after it was attacked by Xerath's followers, and harbors a resentment towards him for his followers' destruction of her hometown."
        },
        {
          "number": "5.3",
          "title": "Captain Indari",
          "link": "#Captain_Indari",
          "children": [],
          "textContent": "Indari was impressed with Samira's bravery and commissioned her to be part of her own private warband. When Indari was caught in an explosion that severely wounded her, Samira risked her life to rescue her at the cost of her own eye. Despite Indari's shame towards her own failure, Samira knew that she understood her desire for thrills more than anybody and proposed to work with her again. Indari now supports Samira behind the scenes by providing her with mercenary work and takes pride in Samira's and determination though she can get frustrated at her recklessness causing trouble, though she has actually been conspiring with LeBlanc without Samira's knowledge."
        },
        {
          "number": "5.4",
          "title": "Lani and  Miel",
          "link": "#Lani_and_Miel",
          "children": [],
          "textContent": "Samira obtained her guns from Lani and Miel, two Noxian gunsmiths."
        },
        {
          "number": "5.5",
          "title": "LeBlanc",
          "link": "#LeBlanc",
          "children": [],
          "textContent": "LeBlanc sees Samira as an important factor in her plans to take over Noxus, so she indirectly manipulates Samira through Indari into carrying out her missions to benefit her own goals."
        },
        {
          "number": "5.6",
          "title": "Rell",
          "link": "#Rell",
          "children": [],
          "textContent": "Samira was unknowingly sent to find Rell under LeBlanc's instruction, by proxy of Indari."
        },
        {
          "number": "5.7",
          "title": "Darius",
          "link": "#Darius",
          "children": [],
          "textContent": "Samira once fought Darius when he was under the influence of the Ruination caused by Viego."
        }
      ]
    },
    {
      "number": "6",
      "title": "Read More",
      "link": "#Read_More",
      "children": [
        {
          "number": "6.1",
          "title": "Biography",
          "link": "#Biography",
          "children": [],
          "textContent": ""
        },
        {
          "number": "6.2",
          "title": "Starring Champion",
          "link": "#Starring_Champion",
          "children": [],
          "textContent": ""
        },
        {
          "number": "6.3",
          "title": "Alternate Universes",
          "link": "#Alternate_Universes",
          "children": [],
          "textContent": ""
        }
      ]
    },
    {
      "number": "7",
      "title": "Trivia",
      "link": "#Trivia",
      "children": [],
      "textContent": ""
    },
    {
      "number": "8",
      "title": "Change log",
      "link": "#Change_log",
      "children": [],
      "textContent": "The following change log is for the Character blurb found at the top of the article:\n\nFor historical versions of other stories, please see each story's respective change log."
    },
    {
      "number": "9",
      "title": "References",
      "link": "#References",
      "children": [],
      "textContent": ""
    },
    {
      "number": "10",
      "title": "See also",
      "link": "#See_also",
      "children": [],
      "textContent": ""
    }
  ],
  "gliner_entities": {
    "Champion": [
      "Viego",
      "Jack",
      "Samira",
      "Darius"
    ],
    "Region": [
      "jungle",
      "Rokrund Plains",
      "southern jungles",
      "Bilgewater",
      "Noxus",
      "Qualthala",
      "Runeterra",
      "Navori"
    ],
    "Weapon": [
      "new guns",
      "specialized blade",
      "basilisks",
      "weapon",
      "the weapon",
      "Immortal Bastion",
      "pair of notably flashy pistols",
      "axes"
    ],
    "Title": [
      "Character blurb",
      "Captain Indari",
      "high-stakes mercenary",
      "mercenary",
      "Indari",
      "rebel leader"
    ],
    "Organization": [
      "weapons shop",
      "warmasons",
      "Noxian gunsmiths",
      "military",
      "empire",
      "Noxus",
      "warband",
      "followers",
      "Lani and Miel Munitions",
      "unit",
      "Noxian noble houses",
      "LeBlanc",
      "Noxian empire",
      "Trifarian Legion"
    ],
    "Family": [
      "parents",
      "her family",
      "her parents"
    ]
  }
}